octodns_route53/__init__.py
octodns_route53/auth.py
octodns_route53/provider.py
octodns_route53/record.py
octodns_route53/source.py
octodns_route53/processor/__init__.py
octodns_route53-1.0.1.dist-info/licenses/LICENSE
octodns_route53-1.0.1.dist-info/METADATA
octodns_route53-1.0.1.dist-info/WHEEL
octodns_route53-1.0.1.dist-info/top_level.txt
octodns_route53-1.0.1.dist-info/RECORD
